{"ID-Nummer": "21.005", "Materialkategorie": "K\u00fccheneinbauten und -m\u00f6bel", "UUID-Nummer": "77DCCEBD-760E-4534-9BF9-975E037EB3A0", "material_name": "Arbeitsplatte kunstharzbeschichtet", "ID-Nummer\nEntsorgung": "91.126", "Entsorgung": "Entsorgung, Arbeitsplatte kunstharzbeschichtet", "Rohdichte (kg/m3)": "", "Bezug": "m2", "Total (UBP) ": "34\u2019300", "Herstellung (UBP) ": "32\u2019800", "Entsorgung (UBP) ": "1\u2019550", "Prim\u00e4renergie Gesamt Total (kWh oil-eq) ": "250", "Prim\u00e4renergie Gesamt Herstellung (kWh oil-eq)": "249", "Prim\u00e4renergie Gesamt Herstellung energetisch genutzt (kWh oil-eq)": "124", "Prim\u00e4renergie Gesamt Herstellung stofflich genutzt (kWh oil-eq)": "125", "Prim\u00e4renergie Gesamt Entsorgung (kWh oil-eq)": "1", "Prim\u00e4renergie erneuerbar Total (kWh oil-eq)": "148", "Prim\u00e4renergie erneuerbar Herstellung Total (kwh oil-eq)": "148", "Prim\u00e4renergie erneuerbar Herstellung energetisch genutzt (kWh oil-eq)": "49", "Prim\u00e4renergie erneuerbar Herstellung stofflich genutzt (kWh oil-eq)": "99", "Prim\u00e4renergie Entsorgung (kWh oil-eq)": "0", "Prim\u00e4renergie nicht erneuerbar Total (kWh oil-eq)": "102", "Prim\u00e4renergie nicht erneuerbar Herstellung Total (kWh oil-eq)": "101", "Prim\u00e4renergie nicht erneuerbar Herstellung energetisch genutzt (kWh oil-eq)": "75", "Prim\u00e4renergie nicht erneuerbar Herstellung stofflich genutzt (kWh oil-eq)": "26", "Prim\u00e4renergie nicht erneuerbar Entsorgung (kWh oil-eq)": "1", "Treibhausgasemissionen Total (kg CO2-eq)": "20.2", "Treibhausgasemissionen Herstellung (kg CO2-eq)": "19", "Treibhausgasemissionen Entsorgung (kg CO2-eq)": "1.2", "Biogener Kohlenstoff im Produkt enthalten (kg C)": "12", "Kommentar": ""}