{"material_ID": "6.001", "Materialkategorie": "Metallbaustoffe", "UUID-Nummer": "122994E0-6AE3-48F8-97C2-633125609F3E", "material_name": "Aluminiumblech, blank", "ID-Nummer Entsorgung": "91.141", "Entsorgung": "Entsorgung, Nichteisenmetalle", "Rohdichte (kg/m3)": "2\u2019690", "Bezug": "kg", "Total (UBP) ": "12\u2019500", "Herstellung (UBP) ": "12\u2019500", "Entsorgung (UBP) ": "19.9", "Prim\u00e4renergie Gesamt Total (kWh oil-eq) ": "30", "Prim\u00e4renergie Gesamt Herstellung (kWh oil-eq)": "30", "Prim\u00e4renergie Gesamt Herstellung energetisch genutzt (kWh oil-eq)": "30", "Prim\u00e4renergie Gesamt Herstellung stofflich genutzt (kWh oil-eq)": "0", "Prim\u00e4renergie Gesamt Entsorgung (kWh oil-eq)": "0", "Prim\u00e4renergie erneuerbar Total (kWh oil-eq)": "5", "Prim\u00e4renergie erneuerbar Herstellung Total (kwh oil-eq)": "5", "Prim\u00e4renergie erneuerbar Herstellung energetisch genutzt (kWh oil-eq)": "5", "Prim\u00e4renergie erneuerbar Herstellung stofflich genutzt (kWh oil-eq)": "0", "Prim\u00e4renergie Entsorgung (kWh oil-eq)": "0", "Prim\u00e4renergie nicht erneuerbar Total (kWh oil-eq)": "25", "Prim\u00e4renergie nicht erneuerbar Herstellung Total (kWh oil-eq)": "25", "Prim\u00e4renergie nicht erneuerbar Herstellung energetisch genutzt (kWh oil-eq)": "25", "Prim\u00e4renergie nicht erneuerbar Herstellung stofflich genutzt (kWh oil-eq)": "0", "Prim\u00e4renergie nicht erneuerbar Entsorgung (kWh oil-eq)": "0", "Treibhausgasemissionen Total (kg CO2-eq)": "5.59", "Treibhausgasemissionen Herstellung (kg CO2-eq)": "5.58", "Treibhausgasemissionen Entsorgung (kg CO2-eq)": "0.00798", "Biogener Kohlenstoff im Produkt enthalten (kg C)": "0", "Kommentar": ""}